{"words":[{"number":1,"value":"АВТОМОБИЛЬ","length":10,"start":{"x":0,"y":0},"orientation":-1},{"number":2,"value":"САМОЛЕТ","length":7,"start":{"x":0,"y":-1},"orientation":1},{"number":3,"value":"КОРАБЛЬ","length":7,"start":{"x":6,"y":-4},"orientation":1},{"number":4,"value":"ТЕЛЕГА","length":6,"start":{"x":8,"y":-2},"orientation":1},{"number":5,"value":"ГРУЗОВИК","length":8,"start":{"x":-1,"y":-4},"orientation":-1}],"clues":[{"number":1,"value":"A structure consisting of an upright and a transverse piece"},{"number":2,"value":"A unit of language"},{"number":3,"value":""},{"number":4,"value":""},{"number":5,"value":""}],"length":5,"indexMap":{"-1,0":"H1","0,0":"А","1,0":"В","2,0":"Т","3,0":"О","4,0":"М","5,0":"О","6,0":"Б","7,0":"И","8,0":"Л","9,0":"Ь","0,-2":"V2","0,-1":"С","0,1":"М","0,2":"О","0,3":"Л","0,4":"Е","0,5":"Т","6,-5":"V3","6,-4":"К","6,-3":"О","6,-2":"Р","6,-1":"А","6,1":"Л","6,2":"Ь","8,-3":"V4","8,-2":"Т","8,-1":"Е","8,1":"Е","8,2":"Г","8,3":"А","-2,-4":"H5","-1,-4":"Г","0,-4":"Р","1,-4":"У","2,-4":"З","3,-4":"О","4,-4":"В","5,-4":"И"},"minXIndex":-2,"maxXIndex":9,"minYIndex":-5,"maxYIndex":5}